bullscatch_backtest/__init__.py
bullscatch_backtest/config.py
bullscatch_backtest/expiry_list_spa.py
bullscatch_backtest/multidate_option_chain_spa.py
bullscatch_backtest/option_chain_spa.py
bullscatch_backtest/spot_fetch_spa.py
bullscatch_backtester-0.2.1.dist-info/METADATA
bullscatch_backtester-0.2.1.dist-info/WHEEL
bullscatch_backtester-0.2.1.dist-info/top_level.txt
bullscatch_backtester-0.2.1.dist-info/RECORD
