Metadata-Version: 2.1
Name: bullscatch_backtester
Version: 0.2.1
Summary: A package for backtesting trading strategies meant for Bullscatch Securities
Author: Guru Pandey
Author-email: guru@bullscatchsecurities.com
Classifier: Programming Language :: Python :: 3
Classifier: License :: OSI Approved :: MIT License
Classifier: Operating System :: OS Independent
Requires-Python: >=3.6
Requires-Dist: pandas
Requires-Dist: psycopg2
